{
    "WBUI2": {
        "settings": {
            "openButton": 1,
            "hideIcon": true,
            "hideIconAfter": 10,
            "iconUrl": "https://i.imgur.com/OZ6xOjY.png",
            "disableIconText": false,
            "iconPosition": 0,
            "iconTextColor": 0,
            "openOnStart": true,
            "openOnStartOnlyForNewPlayers": true,
            "updateInterval": 24
        },
        "tabs": [
            {
                "layout": 1,
                "buttonText": "<RichColor Color=\"1,0,0,1\">Layout 1</>",
                "imageUrl": "https://i.imgur.com/mGt3cAF.png",
                "content": [
                    {
                        "title": "Welcome to WBUI2!",
                        "text": "Your content can go here."
                    }
                ]
            },
            {
                "layout": 5,
                "buttonText": "Open HTML Page",
                "imageUrl": "https://i.imgur.com/mGt3cAF.png",
                "content": [
                    {
                        "title": "HTML Page",
                        "text": "Click the button below to open the HTML page.",
                        "action": {
                            "type": "open_html",
                            "url": "https://example.com"
                        }
                    }
                ]
            }
        ],
        "links": [
            {
                "text": "Wiki Link",
                "url": "https://wiki.wbui2.de"
            },
            {
                "text": "Discord Link",
                "url": "https://discord.com/invite/K7NyrTV"
            },
            {
                "text": "Google Link",
                "url": "https://google.com"
            },
            {
                "text": "HTML Page",
                "url": "https://example.com"
            }
        ],
        "version": 2
    }
}
